MANIFEST.in
README
setup.py
django_password_policies.egg-info/PKG-INFO
django_password_policies.egg-info/SOURCES.txt
django_password_policies.egg-info/dependency_links.txt
django_password_policies.egg-info/not-zip-safe
django_password_policies.egg-info/requires.txt
django_password_policies.egg-info/top_level.txt
password_policies/__init__.py
password_policies/admin.py
password_policies/conf.py
password_policies/context_processors.py
password_policies/managers.py
password_policies/middleware.py
password_policies/models.py
password_policies/urls.py
password_policies/utils.py
password_policies/views.py
password_policies/forms/__init__.py
password_policies/forms/admin.py
password_policies/forms/fields.py
password_policies/forms/validators.py
password_policies/locale/ar/LC_MESSAGES/django.mo
password_policies/locale/ar/LC_MESSAGES/django.po
password_policies/locale/az/LC_MESSAGES/django.mo
password_policies/locale/az/LC_MESSAGES/django.po
password_policies/locale/bg/LC_MESSAGES/django.mo
password_policies/locale/bg/LC_MESSAGES/django.po
password_policies/locale/bn/LC_MESSAGES/django.mo
password_policies/locale/bn/LC_MESSAGES/django.po
password_policies/locale/bs/LC_MESSAGES/django.mo
password_policies/locale/bs/LC_MESSAGES/django.po
password_policies/locale/ca/LC_MESSAGES/django.mo
password_policies/locale/ca/LC_MESSAGES/django.po
password_policies/locale/cs/LC_MESSAGES/django.mo
password_policies/locale/cs/LC_MESSAGES/django.po
password_policies/locale/cy/LC_MESSAGES/django.mo
password_policies/locale/cy/LC_MESSAGES/django.po
password_policies/locale/da/LC_MESSAGES/django.mo
password_policies/locale/da/LC_MESSAGES/django.po
password_policies/locale/de/LC_MESSAGES/django.mo
password_policies/locale/de/LC_MESSAGES/django.po
password_policies/locale/el/LC_MESSAGES/django.mo
password_policies/locale/el/LC_MESSAGES/django.po
password_policies/locale/en/LC_MESSAGES/django.mo
password_policies/locale/en/LC_MESSAGES/django.po
password_policies/locale/en_GB/LC_MESSAGES/django.mo
password_policies/locale/en_GB/LC_MESSAGES/django.po
password_policies/locale/es/LC_MESSAGES/django.mo
password_policies/locale/es/LC_MESSAGES/django.po
password_policies/locale/es_AR/LC_MESSAGES/django.mo
password_policies/locale/es_AR/LC_MESSAGES/django.po
